Metadata-Version: 1.1
Name: melopero-lsm9ds1
Version: 0.1.0
Summary: A module to easily access Melopero's LSM9DS1 sensor's features
Home-page: https://github.com/melopero/Melopero_LSM9DS1
Author: Melopero
Author-email: info@melopero.com
License: MIT
Platform: UNKNOWN
Classifier: Development Status :: 3 - Alpha
Classifier: License :: OSI Approved :: MIT License
Classifier: Programming Language :: Python :: 3
Classifier: Programming Language :: Python :: 3.5
